<?xml version="1.0" encoding="utf-8"?>
	<annotation>
		<folder>OID</folder>
		<filename>11f80fda2c38011c.jpg</filename>
		<source>
			<database>OID car carplate</database>
			<url>https://requestor-proxy.figure-eight.com/figure_eight_datasets/open-images/validation/11f80fda2c38011c.jpg</url>
		</source>
		<size>
			<width>1024</width>
			<height>684</height>
			<depth>3</depth>
		</size>
		<segmented>0</segmented>
		<object>
			<name>carplate</name>
			<pose>Unspecified</pose>
			<occluded>0</occluded>
			<truncated>0</truncated>
			<difficult>0</difficult>
			<bndbox>
				<xmin>540</xmin>
				<ymin>451</ymin>
				<xmax>652</xmax>
				<ymax>493</ymax>
			</bndbox>
		</object>
		<object>
			<name>car</name>
			<pose>Unspecified</pose>
			<occluded>0</occluded>
			<truncated>0</truncated>
			<difficult>0</difficult>
			<bndbox>
				<xmin>250</xmin>
				<ymin>152</ymin>
				<xmax>929</xmax>
				<ymax>601</ymax>
			</bndbox>
		</object>
	</annotation>
