<?xml version="1.0" encoding="utf-8"?>
	<annotation>
		<folder>OID</folder>
		<filename>22f8ca9c07a5dfaf.jpg</filename>
		<source>
			<database>OID car carplate</database>
			<url>https://requestor-proxy.figure-eight.com/figure_eight_datasets/open-images/test/22f8ca9c07a5dfaf.jpg</url>
		</source>
		<size>
			<width>1024</width>
			<height>768</height>
			<depth>3</depth>
		</size>
		<segmented>0</segmented>
		<object>
			<name>carplate</name>
			<pose>Unspecified</pose>
			<occluded>0</occluded>
			<truncated>0</truncated>
			<difficult>0</difficult>
			<bndbox>
				<xmin>452</xmin>
				<ymin>545</ymin>
				<xmax>575</xmax>
				<ymax>612</ymax>
			</bndbox>
		</object>
		<object>
			<name>car</name>
			<pose>Unspecified</pose>
			<occluded>0</occluded>
			<truncated>0</truncated>
			<difficult>0</difficult>
			<bndbox>
				<xmin>205</xmin>
				<ymin>157</ymin>
				<xmax>817</xmax>
				<ymax>672</ymax>
			</bndbox>
		</object>
	</annotation>
