<?xml version="1.0" encoding="utf-8"?>
	<annotation>
		<size>
			<width>1024</width>
			<height>520</height>
			<depth>3</depth>
		</size>
		<url>https://requestor-proxy.figure-eight.com/figure_eight_datasets/open-images/test/3a54b5a73b139f63.jpg</url>
		<object>
			<name>carplate</name>
			<difficult>0</difficult>
			<occluded>0</occluded>
			<truncated>0</truncated>
			<bndbox>
				<xmin>387</xmin>
				<ymin>367</ymin>
				<xmax>554</xmax>
				<ymax>423</ymax>
			</bndbox>
		</object>
		<object>
			<name>carplate</name>
			<difficult>0</difficult>
			<occluded>0</occluded>
			<truncated>0</truncated>
			<bndbox>
				<xmin>855</xmin>
				<ymin>265</ymin>
				<xmax>952</xmax>
				<ymax>298</ymax>
			</bndbox>
		</object>
		<object>
			<name>car</name>
			<difficult>0</difficult>
			<occluded>0</occluded>
			<truncated>0</truncated>
			<bndbox>
				<xmin>38</xmin>
				<ymin>21</ymin>
				<xmax>664</xmax>
				<ymax>484</ymax>
			</bndbox>
		</object>
		<object>
			<name>car</name>
			<difficult>0</difficult>
			<occluded>1</occluded>
			<truncated>0</truncated>
			<bndbox>
				<xmin>408</xmin>
				<ymin>23</ymin>
				<xmax>1002</xmax>
				<ymax>347</ymax>
			</bndbox>
		</object>
	</annotation>
