<?xml version="1.0" encoding="utf-8"?>
	<annotation>
		<size>
			<width>1024</width>
			<height>663</height>
			<depth>3</depth>
		</size>
		<url>https://requestor-proxy.figure-eight.com/figure_eight_datasets/open-images/test/47b81ed691434c8d.jpg</url>
		<object>
			<name>carplate</name>
			<difficult>0</difficult>
			<occluded>0</occluded>
			<truncated>0</truncated>
			<bndbox>
				<xmin>112</xmin>
				<ymin>364</ymin>
				<xmax>206</xmax>
				<ymax>412</ymax>
			</bndbox>
		</object>
		<object>
			<name>car</name>
			<difficult>0</difficult>
			<occluded>0</occluded>
			<truncated>0</truncated>
			<bndbox>
				<xmin>52</xmin>
				<ymin>88</ymin>
				<xmax>967</xmax>
				<ymax>558</ymax>
			</bndbox>
		</object>
	</annotation>
