<?xml version="1.0" encoding="utf-8"?>
	<annotation>
		<size>
			<width>1024</width>
			<height>683</height>
			<depth>3</depth>
		</size>
		<url>https://requestor-proxy.figure-eight.com/figure_eight_datasets/open-images/test/55229893484ce19c.jpg</url>
		<object>
			<name>carplate</name>
			<difficult>0</difficult>
			<occluded>0</occluded>
			<truncated>0</truncated>
			<bndbox>
				<xmin>193</xmin>
				<ymin>466</ymin>
				<xmax>385</xmax>
				<ymax>527</ymax>
			</bndbox>
		</object>
		<object>
			<name>car</name>
			<difficult>0</difficult>
			<occluded>0</occluded>
			<truncated>0</truncated>
			<bndbox>
				<xmin>65</xmin>
				<ymin>28</ymin>
				<xmax>792</xmax>
				<ymax>677</ymax>
			</bndbox>
		</object>
	</annotation>
