<?xml version="1.0" encoding="utf-8"?>
	<annotation>
		<size>
			<width>1024</width>
			<height>768</height>
			<depth>3</depth>
		</size>
		<url>https://requestor-proxy.figure-eight.com/figure_eight_datasets/open-images/test/56951536c6458cad.jpg</url>
		<object>
			<name>carplate</name>
			<difficult>0</difficult>
			<occluded>0</occluded>
			<truncated>0</truncated>
			<bndbox>
				<xmin>377</xmin>
				<ymin>571</ymin>
				<xmax>635</xmax>
				<ymax>629</ymax>
			</bndbox>
		</object>
		<object>
			<name>car</name>
			<difficult>0</difficult>
			<occluded>0</occluded>
			<truncated>0</truncated>
			<bndbox>
				<xmin>60</xmin>
				<ymin>38</ymin>
				<xmax>987</xmax>
				<ymax>732</ymax>
			</bndbox>
		</object>
		<object>
			<name>car</name>
			<difficult>0</difficult>
			<occluded>1</occluded>
			<truncated>0</truncated>
			<bndbox>
				<xmin>793</xmin>
				<ymin>85</ymin>
				<xmax>878</xmax>
				<ymax>142</ymax>
			</bndbox>
		</object>
	</annotation>
